digitalmodel/__init__.py
digitalmodel/__main__.py
digitalmodel/aqwa.py
digitalmodel/catenary_riser_summary.py
digitalmodel/engine.py
digitalmodel/fea_model.py
digitalmodel/time_series.py
digitalmodel/common/ETL_components.py
digitalmodel/common/FEAComponents.py
digitalmodel/common/basic_statistics.py
digitalmodel/common/cathodic_protection.py
digitalmodel/common/code_dnvrph103_hydrodynamics_circular.py
digitalmodel/common/code_dnvrph103_hydrodynamics_rectangular.py
digitalmodel/common/cp_DNV_RP_F103_2010.py
digitalmodel/common/fatigue_analysis.py
digitalmodel/common/pipe_properties.py
digitalmodel/common/plate_buckling.py
digitalmodel/common/plotDefault.py
digitalmodel/common/shear7_model_components.py
digitalmodel/common/ship_design.py
digitalmodel/common/ship_fatigue_analysis.py
digitalmodel/common/typical_riser_stack_up_calculations.py
digitalmodel/common/visualization_components.py
digitalmodel/common/visualization_unused.py
digitalmodel/common/visualizations.py
digitalmodel/common/viv_fatigue_analysis_components.py
digitalmodel/custom/PipeSizing.py
digitalmodel/custom/__init__.py
digitalmodel/custom/aqwa/__init__.py
digitalmodel/custom/aqwa/aqwa_analysis.py
digitalmodel/modules/aqwa/aqwa_analysis.py
digitalmodel/modules/aqwa/aqwa_analysis_damping.py
digitalmodel/modules/aqwa/aqwa_analysis_ef_server.py
digitalmodel/modules/aqwa/aqwa_analysis_raos.py
digitalmodel/modules/aqwa/aqwa_dat_files.py
digitalmodel/modules/aqwa/aqwa_lis_files.py
digitalmodel/modules/aqwa/aqwa_post_process.py
digitalmodel/modules/aqwa/aqwa_pre_process.py
digitalmodel/modules/aqwa/aqwa_reader.py
digitalmodel/modules/aqwa/aqwa_utilities.py
digitalmodel/modules/aqwa/mes_files.py
digitalmodel/modules/aqwa/ef_server/AqwaServerMgr.py
digitalmodel/modules/catenary/__init__.py
digitalmodel/modules/catenary/catenary.py
digitalmodel/modules/catenary/catenaryMethods.py
digitalmodel/modules/catenary/catenaryRiserSummary.py
digitalmodel/modules/catenary/catenary_equation.py
digitalmodel-0.0.9.dist-info/licenses/LICENSE
digitalmodel-0.0.9.dist-info/METADATA
digitalmodel-0.0.9.dist-info/WHEEL
digitalmodel-0.0.9.dist-info/entry_points.txt
digitalmodel-0.0.9.dist-info/top_level.txt
digitalmodel-0.0.9.dist-info/RECORD
