Metadata-Version: 2.4
Name: digitalmodel
Version: 0.0.9
Summary: engineering asset digital model(s) for life cycle analysis
Author-email: Vamsee Achanta <vamsee.achanta@aceengineer.com>
License: MIT
Project-URL: Homepage, https://github.com/vamseeachanta/digitalmodel
Project-URL: Repository, https://github.com/vamseeachanta/digitalmodel
Project-URL: Documentation, https://github.com/vamseeachanta/digitalmodel/blob/master/README.md
Keywords: finite element,asset representation,structural,physical,engineering,animation,lifecycle,lifecycle analysis,single source of truth,digital model,digital twin
Classifier: License :: OSI Approved :: MIT License
Classifier: Programming Language :: Python
Classifier: Programming Language :: Python :: 3
Requires-Python: >=3.8
License-File: LICENSE
Requires-Dist: assetutilities>=0.0.7
Requires-Dist: beautifulsoup4>=4.13.4
Requires-Dist: black>=24.8.0
Requires-Dist: bumpver>=2025.1131
Requires-Dist: dash>=3.1.1
Requires-Dist: deepdiff>=8.4.2
Requires-Dist: docx>=0.2.4
Requires-Dist: imgkit>=1.2.3
Requires-Dist: isort>=5.13.2
Requires-Dist: kaleido>=1.0.0
Requires-Dist: loguru>=0.7.3
Requires-Dist: matplotlib>=3.7.5
Requires-Dist: openpyxl>=3.1.5
Requires-Dist: pandas>=2.0.3
Requires-Dist: plotly>=6.2.0
Requires-Dist: poetry>=1.8.5
Requires-Dist: pydantic>=2.10.6
Requires-Dist: pypdf2>=3.0.1
Requires-Dist: pytest>=8.3.5
Requires-Dist: pyyaml>=6.0.2
Requires-Dist: rainflow>=3.2.0
Requires-Dist: requests>=2.32.4
Requires-Dist: ruamel-yaml>=0.18.14
Requires-Dist: scipy>=1.10.1
Requires-Dist: scrapy>=2.11.2
Requires-Dist: sympy>=1.13.3
Requires-Dist: tabula>=1.0.5
Requires-Dist: tabulate>=0.9.0
Requires-Dist: webcolors>=24.8.0
Requires-Dist: xlrd>=2.0.2
Requires-Dist: xlsxwriter>=3.2.5
Requires-Dist: xmltodict>=0.14.2
Provides-Extra: dev
Requires-Dist: black>=23.0; extra == "dev"
Requires-Dist: bumpver>=2023.1129; extra == "dev"
Requires-Dist: isort>=5.0.0; extra == "dev"
Requires-Dist: pytest>=7.0.0; extra == "dev"
Provides-Extra: deploy
Requires-Dist: twine>=1.0.0; extra == "deploy"
Requires-Dist: build>=1.0.0; extra == "deploy"
Dynamic: license-file
